LAB2/fsm-assignments/problem3_vending/vending_mealy.v
`timescale 1ns/1ns

module vending_mealy (
    input  wire       clk,
    input  wire       rst,       // synchronous active-high reset
    input  wire [1:0] coin,      // 01 = 5, 10 = 10, 00 = idle
    output wire       dispense,  // pulse when vending
    output wire       chg5,      // pulse when change 5 is returned
    output wire [1:0] state_present // debug: current state
);

    // State encoding
    localparam [1:0] ST_IDLE = 2'b00,
                     ST_5    = 2'b01,
                     ST_10   = 2'b10,
                     ST_15   = 2'b11;

    reg [1:0] state_present_reg, state_next;

    // Mealy outputs (combinational)
    reg mealy_disp, mealy_chg;
    // Registered outputs (one cycle pulses)
    reg dispense_reg, chg_reg;

    wire coin5  = (coin == 2'b01);
    wire coin10 = (coin == 2'b10);

    // Combinational next-state + Mealy outputs
    always @(*) begin
        // defaults
        state_next = state_present_reg;
        mealy_disp = 1'b0;
        mealy_chg  = 1'b0;

        case (state_present_reg)
            ST_IDLE: begin
                if (coin5)  state_next = ST_5;
                else if (coin10) state_next = ST_10;
            end

            ST_5: begin
                if (coin5)      state_next = ST_10;
                else if (coin10) state_next = ST_15;
            end

            ST_10: begin
                if (coin5)      state_next = ST_15;
                else if (coin10) begin
                    mealy_disp = 1'b1;
                    state_next = ST_IDLE;
                end
            end

            ST_15: begin
                if (coin5) begin
                    mealy_disp = 1'b1;
                    state_next = ST_IDLE;
                end else if (coin10) begin
                    mealy_disp = 1'b1;
                    mealy_chg  = 1'b1;
                    state_next = ST_IDLE;
                end
            end
        endcase
    end

    // Sequential state + output registers
    always @(posedge clk) begin
        if (rst) begin
            state_present_reg <= ST_IDLE;
            dispense_reg      <= 1'b0;
            chg_reg           <= 1'b0;
        end else begin
            state_present_reg <= state_next;
            dispense_reg      <= mealy_disp;
            chg_reg           <= mealy_chg;
        end
    end

    // Outputs
    assign dispense      = dispense_reg;
    assign chg5          = chg_reg;
    assign state_present = state_present_reg;

endmodule

LAB2/fsm-assignments/problem3_vending/tb_vending_mealy.v
`timescale 1ns/1ns
module tb_vending_mealy;
    reg clk, rst;
    reg [1:0] coin;
    wire dispense, chg5;
    wire [1:0] state_present;

    vending_mealy dut (
        .clk(clk),
        .rst(rst),
        .coin(coin),
        .dispense(dispense),
        .chg5(chg5),
        .state_present(state_present)
    );

    // clock generation (10 ns period)
    initial clk = 0;
    always #5 clk = ~clk;

    initial begin
        $dumpfile("dump.vcd");
        $dumpvars(0, tb_vending_mealy);

        // init
        coin = 2'b00; rst = 1; #20;
        rst = 0; #10; 


        // Scenario: insert 10, then 10 -> vend
        coin = 2'b10; #10; coin = 2'b00; #10;
        coin = 2'b10; #10; coin = 2'b00; #10;

        // Scenario: insert 5, then 5, then 10 -> vend
        coin = 2'b01; #10; coin = 2'b00; #10;
        coin = 2'b01; #10; coin = 2'b00; #10;
        coin = 2'b10; #10; coin = 2'b00; #10;

        // Scenario: insert 15 (5+10), then 10 -> vend + change
        coin = 2'b01; #10; coin = 2'b00; #10;
        coin = 2'b10; #10; coin = 2'b00; #10;
        coin = 2'b10; #10; coin = 2'b00; #10;

        #50; $finish;
    end

    initial begin
        $monitor("%0t | clk=%b coin=%b state=%0d dispense=%b chg5=%b", $time, clk, coin, state_present, dispense, chg5);
    end
endmodule

LAB2/fsm-assignments/problem3_vending/dump.vcd
$date
	Mon Aug 18 22:54:37 2025
$end
$version
	Icarus Verilog
$end
$timescale
	1ps
$end
$scope module tb_vending_mealy $end
$var wire 2 ! state_present [1:0] $end
$var wire 1 " dispense $end
$var wire 1 # chg5 $end
$var reg 1 $ clk $end
$var reg 2 % coin [1:0] $end
$var reg 1 & rst $end
$scope module dut $end
$var wire 1 # chg5 $end
$var wire 1 $ clk $end
$var wire 2 ' coin [1:0] $end
$var wire 1 " dispense $end
$var wire 1 & rst $end
$var wire 2 ( state_present [1:0] $end
$var wire 1 ) coin5 $end
$var wire 1 * coin10 $end
$var reg 1 + chg_reg $end
$var reg 1 , dispense_reg $end
$var reg 1 - mealy_chg $end
$var reg 1 . mealy_disp $end
$var reg 2 / state_next [1:0] $end
$var reg 2 0 state_present_reg [1:0] $end
$upscope $end
$upscope $end
$enddefinitions $end
#0
$dumpvars
bx 0
bx /
0.
0-
x,
x+
0*
0)
bx (
b0 '
1&
b0 %
0$
x#
x"
bx !
$end
#5000
b0 /
0#
0+
0"
0,
b0 !
b0 (
b0 0
1$
#10000
0$
#15000
1$
#20000
0$
0&
#25000
1$
#30000
b10 /
0$
1*
b10 %
b10 '
#35000
b0 /
1.
b10 !
b10 (
b10 0
1$
#40000
0.
b10 /
0$
0*
b0 %
b0 '
#45000
1$
#50000
b0 /
1.
0$
1*
b10 %
b10 '
#55000
b10 /
0.
1"
1,
b0 !
b0 (
b0 0
1$
#60000
b0 /
0$
0*
b0 %
b0 '
#65000
0"
0,
1$
#70000
b1 /
0$
1)
b1 %
b1 '
#75000
b10 /
b1 !
b1 (
b1 0
1$
#80000
b1 /
0$
0)
b0 %
b0 '
#85000
1$
#90000
b10 /
0$
1)
b1 %
b1 '
#95000
b11 /
b10 !
b10 (
b10 0
1$
#100000
b10 /
0$
0)
b0 %
b0 '
#105000
1$
#110000
b0 /
1.
0$
1*
b10 %
b10 '
#115000
b10 /
0.
1"
1,
b0 !
b0 (
b0 0
1$
#120000
b0 /
0$
0*
b0 %
b0 '
#125000
0"
0,
1$
#130000
b1 /
0$
1)
b1 %
b1 '
#135000
b10 /
b1 !
b1 (
b1 0
1$
#140000
b1 /
0$
0)
b0 %
b0 '
#145000
1$
#150000
b11 /
0$
1*
b10 %
b10 '
#155000
b0 /
1-
1.
b11 !
b11 (
b11 0
1$
#160000
0-
0.
b11 /
0$
0*
b0 %
b0 '
#165000
1$
#170000
b0 /
1-
1.
0$
1*
b10 %
b10 '
#175000
b10 /
0-
0.
1#
1+
1"
1,
b0 !
b0 (
b0 0
1$
#180000
b0 /
0$
0*
b0 %
b0 '
#185000
0#
0+
0"
0,
1$
